[{"Fournisseur":"Risen Energy","Modele":"RSM120-6-310P","PuissanceMaximale":310,"RendementDuPanneau":"18,40%"},{"Fournisseur":"Risen Energy","Modele":"RSM120-6-315P","PuissanceMaximale":315,"RendementDuPanneau":"18,70%"},{"Fournisseur":"Risen Energy","Modele":"RSM120-6-320P","PuissanceMaximale":320,"RendementDuPanneau":"19,00%"},{"Fournisseur":"Risen Energy","Modele":"RSM120-6-325P","PuissanceMaximale":325,"RendementDuPanneau":"19,30%"},{"Fournisseur":"Risen Energy","Modele":"RSM120-6-330P","PuissanceMaximale":330,"RendementDuPanneau":"19,60%"},{"Fournisseur":"Risen Energy","Modele":"RSM120-6-330M","PuissanceMaximale":330,"RendementDuPanneau":"19,60%"},{"Fournisseur":"Risen Energy","Modele":"RSM120-6-335M","PuissanceMaximale":335,"RendementDuPanneau":"19,90%"},{"Fournisseur":"Risen Energy","Modele":"RSM120-6-340M","PuissanceMaximale":340,"RendementDuPanneau":"20,20%"},{"Fournisseur":"Risen Energy","Modele":"RSM120-6-345M","PuissanceMaximale":345,"RendementDuPanneau":"20,50%"},{"Fournisseur":"Risen Energy","Modele":"RSM120-6-350M","PuissanceMaximale":350,"RendementDuPanneau":"20,80%"},{"Fournisseur":"Hanwha Q-Cells","Modele":"Q.PEAK DUO-G5 315","PuissanceMaximale":315,"RendementDuPanneau":"18,70%"},{"Fournisseur":"Hanwha Q-Cells","Modele":"Q.PEAK DUO-G5 320","PuissanceMaximale":320,"RendementDuPanneau":"19,00%"},{"Fournisseur":"Hanwha Q-Cells","Modele":"Q.PEAK DUO-G5 325","PuissanceMaximale":325,"RendementDuPanneau":"19,30%"},{"Fournisseur":"Hanwha Q-Cells","Modele":"Q.PEAK DUO-G5 330","PuissanceMaximale":330,"RendementDuPanneau":"19,60%"},{"Fournisseur":"Hanwha Q-Cells","Modele":"Q.PEAK-G4.1 290","PuissanceMaximale":290,"RendementDuPanneau":"17,40%"},{"Fournisseur":"Hanwha Q-Cells","Modele":"Q.PEAK-G4.1 295","PuissanceMaximale":295,"RendementDuPanneau":"17,70%"},{"Fournisseur":"Hanwha Q-Cells","Modele":"Q.PEAK-G4.1 300","PuissanceMaximale":300,"RendementDuPanneau":"18,00%"},{"Fournisseur":"Hanwha Q-Cells","Modele":"Q.PEAK-G4.1 305","PuissanceMaximale":305,"RendementDuPanneau":"18,30%"},{"Fournisseur":"Hanwha Q-Cells","Modele":"Q.PEAK-G4.1 310","PuissanceMaximale":310,"RendementDuPanneau":"18,60%"},{"Fournisseur":"Hanwha Q-Cells","Modele":"Q.PRIME L-G5 325","PuissanceMaximale":325,"RendementDuPanneau":"16,70%"},{"Fournisseur":"Hanwha Q-Cells","Modele":"Q.PRIME L-G5 330","PuissanceMaximale":330,"RendementDuPanneau":"16,90%"},{"Fournisseur":"Hanwha Q-Cells","Modele":"Q.PRIME L-G5 335","PuissanceMaximale":335,"RendementDuPanneau":"17,20%"},{"Fournisseur":"Hanwha Q-Cells","Modele":"Q.PRIME L-G5 340","PuissanceMaximale":340,"RendementDuPanneau":"17,50%"},{"Fournisseur":"Hanwha Q-Cells","Modele":"Q.PRIME L-G5 345","PuissanceMaximale":345,"RendementDuPanneau":"17,70%"},{"Fournisseur":"Hanwha Q-Cells","Modele":"Q.PEAK-G5 295","PuissanceMaximale":295,"RendementDuPanneau":"18,00%"},{"Fournisseur":"Hanwha Q-Cells","Modele":"Q.PEAK-G5 300","PuissanceMaximale":300,"RendementDuPanneau":"18,30%"},{"Fournisseur":"Hanwha Q-Cells","Modele":"Q.PEAK-G5 305","PuissanceMaximale":305,"RendementDuPanneau":"18,70%"},{"Fournisseur":"Hanwha Q-Cells","Modele":"Q.PEAK-G5 310","PuissanceMaximale":310,"RendementDuPanneau":"19,00%"},{"Fournisseur":"Hanwha Q-Cells","Modele":"Q.PEAK BLK-G4.1 285","PuissanceMaximale":285,"RendementDuPanneau":"17,10%"},{"Fournisseur":"Hanwha Q-Cells","Modele":"Q.PEAK BLK-G4.1 290","PuissanceMaximale":290,"RendementDuPanneau":"17,40%"},{"Fournisseur":"Hanwha Q-Cells","Modele":"Q.PEAK BLK-G4.1 295","PuissanceMaximale":295,"RendementDuPanneau":"17,70%"},{"Fournisseur":"Hanwha Q-Cells","Modele":"Q.PEAK BLK-G4.1 300","PuissanceMaximale":300,"RendementDuPanneau":"18,00%"},{"Fournisseur":"Trina Solar","Modele":"ALLMAX M Plus 275","PuissanceMaximale":275,"RendementDuPanneau":"16,80%"},{"Fournisseur":"Trina Solar","Modele":"ALLMAX M Plus 280","PuissanceMaximale":280,"RendementDuPanneau":"17,10%"},{"Fournisseur":"Trina Solar","Modele":"ALLMAX M Plus 285","PuissanceMaximale":285,"RendementDuPanneau":"17,40%"},{"Fournisseur":"Trina Solar","Modele":"ALLMAX M Plus 290","PuissanceMaximale":280,"RendementDuPanneau":"17,70%"},{"Fournisseur":"Trina Solar","Modele":"ALLMAX M Plus 295","PuissanceMaximale":285,"RendementDuPanneau":"18,00%"},{"Fournisseur":"Trina Solar","Modele":"ALLMAX M Plus 300","PuissanceMaximale":300,"RendementDuPanneau":"18,30%"},{"Fournisseur":"Trina Solar","Modele":"ALLMAX M Plus 305","PuissanceMaximale":305,"RendementDuPanneau":"18,60%"},{"Fournisseur":"Trina Solar","Modele":"ALLMAX M Plus 310","PuissanceMaximale":310,"RendementDuPanneau":"18,90%"},{"Fournisseur":"Trina Solar","Modele":"ALLMAX M Plus 315","PuissanceMaximale":315,"RendementDuPanneau":"19,20%"},{"Fournisseur":"Trina Solar","Modele":"DUOMAX M Plus 280","PuissanceMaximale":280,"RendementDuPanneau":"17,00%"},{"Fournisseur":"Trina Solar","Modele":"DUOMAX M Plus 285","PuissanceMaximale":285,"RendementDuPanneau":"17,30%"},{"Fournisseur":"Trina Solar","Modele":"DUOMAX M Plus 290","PuissanceMaximale":290,"RendementDuPanneau":"17,60%"},{"Fournisseur":"Trina Solar","Modele":"DUOMAX M Plus 295","PuissanceMaximale":295,"RendementDuPanneau":"17,90%"},{"Fournisseur":"Trina Solar","Modele":"DUOMAX M Plus 300","PuissanceMaximale":300,"RendementDuPanneau":"18,20%"},{"Fournisseur":"Trina Solar","Modele":"DUOMAX M Plus 305","PuissanceMaximale":305,"RendementDuPanneau":"18,50%"},{"Fournisseur":"Trina Solar","Modele":"DUOMAX M Plus 310","PuissanceMaximale":310,"RendementDuPanneau":"18,80%"},{"Fournisseur":"Trina Solar","Modele":"DUOMAX M Plus 315","PuissanceMaximale":315,"RendementDuPanneau":"19,20%"},{"Fournisseur":"Trina Solar","Modele":"ALLMAX M PLUS Half-Cut 285","PuissanceMaximale":285,"RendementDuPanneau":"17,20%"},{"Fournisseur":"Trina Solar","Modele":"ALLMAX M PLUS Half-Cut 290","PuissanceMaximale":290,"RendementDuPanneau":"17,50%"},{"Fournisseur":"Trina Solar","Modele":"ALLMAX M PLUS Half-Cut 295","PuissanceMaximale":295,"RendementDuPanneau":"17,80%"},{"Fournisseur":"Trina Solar","Modele":"ALLMAX M PLUS Half-Cut 300","PuissanceMaximale":300,"RendementDuPanneau":"18,10%"},{"Fournisseur":"Trina Solar","Modele":"ALLMAX M PLUS Half-Cut 305","PuissanceMaximale":305,"RendementDuPanneau":"18,40%"},{"Fournisseur":"Trina Solar","Modele":"ALLMAX M PLUS Half-Cut 310","PuissanceMaximale":310,"RendementDuPanneau":"18,70%"},{"Fournisseur":"Trina Solar","Modele":"ALLMAX M PLUS Half-Cut 315","PuissanceMaximale":315,"RendementDuPanneau":"19,00%"},{"Fournisseur":"Trina Solar","Modele":"ALLMAX M PLUS Half-Cut 320","PuissanceMaximale":320,"RendementDuPanneau":"19,30%"},{"Fournisseur":"Trina Solar","Modele":"ALLMAX M PLUS Half-Cut 320","PuissanceMaximale":320,"RendementDuPanneau":"18,80%"},{"Fournisseur":"Trina Solar","Modele":"ALLMAX M PLUS Half-Cut 325","PuissanceMaximale":325,"RendementDuPanneau":"19,10%"},{"Fournisseur":"Trina Solar","Modele":"ALLMAX M PLUS Half-Cut 330","PuissanceMaximale":330,"RendementDuPanneau":"19,40%"},{"Fournisseur":"Trina Solar","Modele":"ALLMAX M PLUS Half-Cut 335","PuissanceMaximale":335,"RendementDuPanneau":"19,70%"},{"Fournisseur":"Trina Solar","Modele":"Residential Module Half-Cut 310","PuissanceMaximale":310,"RendementDuPanneau":"18,20%"},{"Fournisseur":"Trina Solar","Modele":"Residential Module Half-Cut 315","PuissanceMaximale":315,"RendementDuPanneau":"18,50%"},{"Fournisseur":"Trina Solar","Modele":"Residential Module Half-Cut 320","PuissanceMaximale":320,"RendementDuPanneau":"18,80%"},{"Fournisseur":"Trina Solar","Modele":"Residential Module Half-Cut 325","PuissanceMaximale":325,"RendementDuPanneau":"19,10%"},{"Fournisseur":"Trina Solar","Modele":"Residential Module Half-Cut 330","PuissanceMaximale":330,"RendementDuPanneau":"19,40%"},{"Fournisseur":"Trina Solar","Modele":"Residential Module Half-Cut 335","PuissanceMaximale":335,"RendementDuPanneau":"19,70%"},{"Fournisseur":"Trina Solar","Modele":"DUOMAX M Plus 340","PuissanceMaximale":340,"RendementDuPanneau":"17,30%"},{"Fournisseur":"Trina Solar","Modele":"DUOMAX M Plus 345","PuissanceMaximale":345,"RendementDuPanneau":"17,60%"},{"Fournisseur":"Trina Solar","Modele":"DUOMAX M Plus 350","PuissanceMaximale":350,"RendementDuPanneau":"17,80%"},{"Fournisseur":"Trina Solar","Modele":"TALLMAX M PLUS Half-Cut 345","PuissanceMaximale":345,"RendementDuPanneau":"17,40%"},{"Fournisseur":"Trina Solar","Modele":"TALLMAX M PLUS Half-Cut 350","PuissanceMaximale":350,"RendementDuPanneau":"17,60%"},{"Fournisseur":"Trina Solar","Modele":"TALLMAX M Plus 340","PuissanceMaximale":340,"RendementDuPanneau":"17,40%"},{"Fournisseur":"Trina Solar","Modele":"TALLMAX M Plus 345","PuissanceMaximale":345,"RendementDuPanneau":"17,70%"},{"Fournisseur":"Trina Solar","Modele":"TALLMAX M Plus 350","PuissanceMaximale":350,"RendementDuPanneau":"18,00%"}]
